{
    "members": [
        "332543151367651341",
        "288643530971414528"
    ],
    "channelid": 1029433021029421106,
    "name": "Ceiko",
    "start": "2022-10-11 19:36:10.003117",
    "points": 22,
    "currentEasyTask": 30,
    "currentMediumTask": 102,
    "currentHardTask": -1,
    "easyAmt": 0,
    "mediumAmt": 0,
    "hardAmt": 22,
    "completedTasks": [
        112,
        114,
        115,
        116,
        117,
        118,
        119,
        120,
        121,
        122,
        123,
        124,
        125,
        126,
        127,
        128,
        129,
        130,
        131,
        132,
        111,
        112
    ],
    "end": "2022-10-11 19:36:10.003129"
}